LICENSE.rst
README.md
setup.cfg
setup.py
src/namespaced_enums.py
src/namespaced_enums.egg-info/PKG-INFO
src/namespaced_enums.egg-info/SOURCES.txt
src/namespaced_enums.egg-info/dependency_links.txt
src/namespaced_enums.egg-info/top_level.txt