Metadata-Version: 2.1
Name: namespaced-enums
Version: 0.0.2
Summary: UNKNOWN
Home-page: https://github.com/waszker/namespaced_enums
Author: Piotr Waszkiewicz
Author-email: waszka23@gmail.com
License: MIT
Project-URL: Bug Reports, https://github.com/waszker/namespaced_enums/issues
Project-URL: Source, https://github.com/waszker/namespaced_enums
Keywords: python,enum,namespaced
Platform: UNKNOWN
Classifier: Development Status :: 3 - Alpha
Classifier: Intended Audience :: Developers
Classifier: Topic :: Software Development :: Build Tools
Classifier: License :: OSI Approved :: MIT License
Classifier: Programming Language :: Python :: 3
Classifier: Programming Language :: Python :: 3.7
Classifier: Programming Language :: Python :: 3.8
Classifier: Programming Language :: Python :: 3.9
Classifier: Programming Language :: Python :: 3.10
Classifier: Programming Language :: Python :: 3.11
Classifier: Programming Language :: Python :: 3 :: Only
Requires-Python: >=3.7, <4
License-File: LICENSE.rst
